{"type":"PR","pr":{"number":22,"head":"afd31031b1eead2833119e3aeb3056318b83d992"},"user":"boukahilat.f","status":"pending_publish","branch":"cms/2018-07-03-prêt-emprunt-et-crédit-immobilier-en-algérie-tout-ce-qu’il-faut-savoir","collection":"blog","title":"Prêt, emprunt et crédit immobilier en Algérie : Tout ce qu’il faut savoir","description":" les conditions d'obtention d'un crédit immobilier en Algérie tout ce qu'il faut savoir, dossier bancaire à fournir  ","objects":{"entry":{"path":"_posts/2018-07-03-prêt-emprunt-et-crédit-immobilier-en-algérie-tout-ce-qu’il-faut-savoir.md","sha":"7f5c857cb2396f49be2700c4482edd0a5a308e34"},"files":[]},"timeStamp":"2018-07-04T12:15:08.536Z"}